<Properties StartupConfiguration="{E9E6AF51-96C9-416C-BF48-29AE43CAFEE5}|Default">
  <MonoDevelop.Ide.Workbench>
    <Files>
      <File FileName="CodingChallenge/Program.cs" Line="24" Column="54" />
      <File FileName="CodingChallenge/CircleDiff.cs" Line="9" Column="23" />
    </Files>
    <Pads>
      <Pad Id="ProjectPad">
        <State name="__root__">
          <Node name="CodingChallenge" expanded="True">
            <Node name="CodingChallenge" expanded="True">
              <Node name="CircleDiff.cs" selected="True" />
            </Node>
          </Node>
        </State>
      </Pad>
    </Pads>
  </MonoDevelop.Ide.Workbench>
  <MonoDevelop.Ide.DebuggingService.PinnedWatches />
  <MonoDevelop.Ide.ItemProperties.CodingChallenge PreferredExecutionTarget="MonoDevelop.Default" />
  <MonoDevelop.Ide.Workspace ActiveConfiguration="Debug" />
  <MonoDevelop.Ide.DebuggingService.Breakpoints>
    <BreakpointStore />
  </MonoDevelop.Ide.DebuggingService.Breakpoints>
  <MultiItemStartupConfigurations />
</Properties>